MANIFEST.in
README
README.rst
setup.cfg
setup.py
docs/CHANGELOG
docs/LICENSE
docs/README
docs/ROADMAP
docs/__init__.py
docs/eazytext.etx
docs/getstarted.etx
docs/parsetab.py
docs/plugins.etx
docs/primer.etx
docs/skins.etx
docs/styleshortcuts.etx
docs/dev/eazytext-spec.etx
eazytext/__init__.py
eazytext/ast.py
eazytext/codegen.py
eazytext/compiler.py
eazytext/eztext.py
eazytext/interfaces.py
eazytext/lexer.py
eazytext/parser.py
eazytext/runtime.py
eazytext/style.py
eazytext/ttags.py
eazytext/utils.py
eazytext.egg-info/PKG-INFO
eazytext.egg-info/SOURCES.txt
eazytext.egg-info/dependency_links.txt
eazytext.egg-info/entry_points.txt
eazytext.egg-info/namespace_packages.txt
eazytext.egg-info/requires.txt
eazytext.egg-info/top_level.txt
eazytext.egg-info/zip-safe
eazytext/extension/__init__.py
eazytext/extension/code.py
eazytext/extension/frontpage.py
eazytext/extension/nested.py
eazytext/extension/ttlpygment.py
eazytext/macro/__init__.py
eazytext/macro/anchor.py
eazytext/macro/clear.py
eazytext/macro/html.py
eazytext/macro/image.py
eazytext/macro/images.py
eazytext/macro/redirect.py
eazytext/macro/span.py
eazytext/macro/toc.py
eazytext/macro/yearsbefore.py
eazytext/skins/default.css
eazytext/templates/tablesorter.js
eazytext/templates/zwextbox.js
eazytext/test/__init__.py
eazytext/test/parsetab.py
eazytext/test/testmixchar.py
eazytext/test/testmixline.py
eazytext/test/teststd.py
eazytext/test/stdfiles/basictext1.etx
eazytext/test/stdfiles/bquotes1.etx
eazytext/test/stdfiles/bquotes2.etx
eazytext/test/stdfiles/bquotes3.etx
eazytext/test/stdfiles/bquotes4.etx
eazytext/test/stdfiles/bquotes5.etx
eazytext/test/stdfiles/btbl1.etx
eazytext/test/stdfiles/btbl2.etx
eazytext/test/stdfiles/def1.etx
eazytext/test/stdfiles/def2.etx
eazytext/test/stdfiles/def3.etx
eazytext/test/stdfiles/extension.etx
eazytext/test/stdfiles/frontpage.etx
eazytext/test/stdfiles/html.etx
eazytext/test/stdfiles/link.etx
eazytext/test/stdfiles/list1.etx
eazytext/test/stdfiles/list2.etx
eazytext/test/stdfiles/list3.etx
eazytext/test/stdfiles/list4.etx
eazytext/test/stdfiles/liststyle.etx
eazytext/test/stdfiles/macro.etx
eazytext/test/stdfiles/markuptext1.etx
eazytext/test/stdfiles/markuptext2.etx
eazytext/test/stdfiles/markuptext3.etx
